claire_sensor/__init__.py
claire_sensor/main.py
claire_sensor/operations.py
claire_sensor/protocol.py
claire_sensor-0.0.2.dist-info/METADATA
claire_sensor-0.0.2.dist-info/WHEEL
claire_sensor-0.0.2.dist-info/entry_points.txt
claire_sensor-0.0.2.dist-info/top_level.txt
claire_sensor-0.0.2.dist-info/RECORD
