Metadata-Version: 2.4
Name: claire-sensor
Version: 0.0.2
Summary: Claire-sensor is an simple agent to execute commands for Claire Test suite
Author-email: Michal Toth <mtoth@redhat.com>
License: MIT
Requires-Dist: fastapi
Requires-Dist: uvicorn
